mustrd/README.adoc
mustrd/README.md
mustrd/TestResult.py
mustrd/__init__.py
mustrd/anzo_utils.py
mustrd/logger_setup.py
mustrd/model/catalog-v001.xml
mustrd/model/mustrdShapes.ttl
mustrd/model/mustrdTestOntology.ttl
mustrd/model/mustrdTestShapes.ttl
mustrd/model/ontology.ttl
mustrd/model/test-resources/resources.ttl
mustrd/model/triplestoreOntology.ttl
mustrd/model/triplestoreshapes.ttl
mustrd/mustrd.py
mustrd/mustrdAnzo.py
mustrd/mustrdGraphDb.py
mustrd/mustrdRdfLib.py
mustrd/mustrdTestPlugin.py
mustrd/namespace.py
mustrd/run.py
mustrd/spec_component.py
mustrd/steprunner.py
mustrd/templates/md_ResultList_leaf_template.jinja
mustrd/templates/md_ResultList_template.jinja
mustrd/templates/md_stats_template.jinja
mustrd/utils.py
mustrd-0.7.4.dist-info/LICENSE
mustrd-0.7.4.dist-info/METADATA
mustrd-0.7.4.dist-info/WHEEL
mustrd-0.7.4.dist-info/entry_points.txt
mustrd-0.7.4.dist-info/RECORD
