Metadata-Version: 2.3
Name: mustrd
Version: 0.7.4
Summary: A Spec By Example framework for RDF and SPARQL, Inspired by Cucumber.
License: MIT
Author: John Placek
Author-email: john.placek@semanticpartners.com
Requires-Python: >=3.10,<4.0
Classifier: Programming Language :: Python
Classifier: Framework :: Pytest
Classifier: Natural Language :: English
Classifier: Topic :: Software Development :: Quality Assurance
Classifier: Topic :: Software Development :: Testing
Classifier: Topic :: Utilities
Requires-Dist: Jinja2 (==3.1.5)
Requires-Dist: beautifulsoup4 (>=4.11.1,<5.0.0)
Requires-Dist: colorama (==0.4.6)
Requires-Dist: colorlog (>=6.7.0,<7.0.0)
Requires-Dist: coverage (==7.4.3)
Requires-Dist: edn-format (>=0.7.5,<0.8.0)
Requires-Dist: flake8 (==7.0.0)
Requires-Dist: multimethods-py (>=0.5.3,<0.6.0)
Requires-Dist: numpy (>=1.26.0,<1.27.0)
Requires-Dist: openpyxl (>=3.1.2,<4.0.0)
Requires-Dist: pandas (>=2.0,<3.0)
Requires-Dist: pyshacl (>=0.30.0,<0.31.0)
Requires-Dist: pytest (>=7.2.0,<8.0.0)
Requires-Dist: rdflib (>=7.1.3,<8.0.0)
Requires-Dist: requests (>=2.28.2,<3.0.0)
Requires-Dist: tabulate (>=0.9.0,<0.10.0)
Requires-Dist: toml (>=0.10.2,<0.11.0)
Requires-Dist: tomli (>=2.0.1,<3.0.0)
Requires-Dist: urllib3 (==1.26.19)
Project-URL: Repository, https://github.com/Semantic-partners/mustrd
